snappy_gpt/GPT.py
snappy_gpt/__init__.py
snappy_gpt/utils.py
snappy_gpt-0.0.1.dist-info/METADATA
snappy_gpt-0.0.1.dist-info/WHEEL
snappy_gpt-0.0.1.dist-info/licenses/LICENSE
snappy_gpt-0.0.1.dist-info/RECORD
