Metadata-Version: 2.3
Name: snappy_gpt
Version: 0.0.1
Summary: Another Wrapper for ESA Snap Graph Processing Tool
Project-URL: Homepage, https://gitlab.com/SteffenME1/snappy-gpt
Project-URL: Issues, https://gitlab.com/SteffenME1/snappy-gpt/-/issues
Author-email: Steffen Merseburg <steffen.merseburg@space-eye.org>
License-File: LICENSE
Classifier: License :: OSI Approved :: MIT License
Classifier: Operating System :: OS Independent
Classifier: Programming Language :: Python :: 3
Requires-Python: >=3.8
